[
  {
    "id": "canada",
    "name": "Canada",
    "owner": "gayathri-rp-19560",
    "description": "Design tokens for Canada"
  },
  {
    "id": "desktop-pdf-editor",
    "name": "Desktop PDF Editor",
    "owner": "sridhar-ravi-2917",
    "description": "Default project ГѓВѓГ‚ВўГѓВ‚Г‚ВЂГѓВ‚Г‚В” the original DTF token set for the Desktop PDF Editor product."
  },
  {
    "id": "writer-handhelds",
    "name": "writer-handhelds",
    "owner": "sridhar-ravi-2917",
    "description": ""
  },
  {
    "id": "calicut",
    "name": "Calicut",
    "owner": "gayathri-rp-19560",
    "description": "Design tokens for Calicut"
  }
]
